gpx2kml/__init__.py
gpx2kml/gpx.py
gpx2kml/kml.py
gpx2kml/util.py
gpx2kml-0.1.1.dist-info/licenses/LICENSE
gpx2kml-0.1.1.dist-info/METADATA
gpx2kml-0.1.1.dist-info/WHEEL
gpx2kml-0.1.1.dist-info/entry_points.txt
gpx2kml-0.1.1.dist-info/top_level.txt
gpx2kml-0.1.1.dist-info/RECORD
