Metadata-Version: 2.4
Name: gpx2kml
Version: 0.1.1
Summary: A library to combine gpx files exported from runkeeper.com to kml files
Author-email: Kan Fu <fukan.thu@gmail.com>
Project-URL: Homepage, https://github.com/kan-fu/gpx2kml
Project-URL: Bug Tracker, https://github.com/kan-fu/gpx2kml/issues
Classifier: Programming Language :: Python :: 3
Classifier: License :: OSI Approved :: MIT License
Classifier: Operating System :: OS Independent
Requires-Python: >=3.10
License-File: LICENSE
Provides-Extra: dev
Requires-Dist: tox; extra == "dev"
Requires-Dist: pytest; extra == "dev"
Dynamic: license-file
